{
	"data": {
		"COLLECTED": {
			"COUNT_PERSONS": { "COLLECTED": 5 },
			"PRENOMS": {
				"COLLECTED": ["Beyoncé", "Jay-Z", "Blue Ivy", "Rumi", "Sir"]
			},
			"NOMS": {
				"COLLECTED": ["Knowles", "Carter", "Carter", "Carter", "Carter"]
			},
			"DATENAISS": {
				"COLLECTED": [
					"1981-09-04",
					"1969-12-04",
					"2012-01-07",
					"2017-06-13",
					"2017-06-13"
				]
			},
			"SEXES": { "COLLECTED": ["2", "1", "2", "2", "1"] },
			"NATIO": { "COLLECTED": [] },
			"OUESTVOUSNECOMMUNE": { "COLLECTED": [] },
			"VIVEZVOUSDS": { "COLLECTED": ["1", "2", "1", "1", "1"] },
			"QUELSSONTL_IRIS": { "COLLECTED": "IRIS" }
		}
	},
	"stateData": {
		"state": "INITIAL",
		"date": 132583235000,
		"currentPage": "20"
	},
	"personalization": []
}
